image_processing/__init__.py
image_processing/processing/__init__.py
image_processing/processing/combination.py
image_processing/processing/transformation.py
image_processing/util/__init__.py
image_processing/util/io.py
image_processing/util/plot.py
Processando_Imagens-0.0.5.dist-info/METADATA
Processando_Imagens-0.0.5.dist-info/WHEEL
Processando_Imagens-0.0.5.dist-info/top_level.txt
Processando_Imagens-0.0.5.dist-info/RECORD
