Metadata-Version: 2.1
Name: Processando-Imagens
Version: 0.0.5
Summary: Pacote de processamento de imagem usando Skimage
Home-page: https://github.com/Jair-pc/Dio_Processamento_de_imagens_em_Python
Author: Jair Pereira
Author-email: juniorpsilva@msn.com
Requires-Python: >=3.8
Requires-Dist: matplotlib
Requires-Dist: numpy
Requires-Dist: scikit-image (>=0.16.1)
